bool_hybrid_array/__init__.py
bool_hybrid_array/__main__.py
bool_hybrid_array/_cppiostream.py
bool_hybrid_array/compile_core.cp314-win_amd64.pyd
bool_hybrid_array/core.c
bool_hybrid_array/core.py
bool_hybrid_array/秘密.md
bool_hybrid_array/int_array/__init__.py
bool_hybrid_array/int_array/core.py
bool_hybrid_array-9.11.12.dist-info/licenses/LICENSE
bool_hybrid_array-9.11.12.dist-info/METADATA
bool_hybrid_array-9.11.12.dist-info/WHEEL
bool_hybrid_array-9.11.12.dist-info/top_level.txt
bool_hybrid_array-9.11.12.dist-info/RECORD
