Metadata-Version: 2.4
Name: bool-hybrid-array
Version: 9.11.12
Summary: 一个高效的布尔数组（密集+稀疏混合存储，节省内存）
Home-page: https://github.com/BKsell/bool-hybrid-array
Author: 蔡靖杰
Author-email: 1289270215@qq.com
Project-URL: GitHub 主站, https://github.com/BKsell/bool-hybrid-array
Project-URL: GitHub 中文镜像, https://www.github-zh.com/projects/1083175506-bool-hybrid-array
Project-URL: Issue 反馈（主站）, https://github.com/BKsell/bool-hybrid-array/issues
Keywords: boolean array,compact storage
Classifier: Programming Language :: Cython
Classifier: Programming Language :: Python
Classifier: Programming Language :: Python :: 3
Classifier: Programming Language :: Python :: 3.8
Classifier: Programming Language :: Python :: 3.9
Classifier: Programming Language :: Python :: 3.10
Classifier: Programming Language :: Python :: 3.11
Classifier: Programming Language :: Python :: 3.12
Classifier: Programming Language :: Python :: 3.13
Classifier: Programming Language :: Python :: 3.14
Classifier: Programming Language :: Python :: 3 :: Only
Classifier: Programming Language :: Python :: Implementation :: CPython
Classifier: Programming Language :: Python :: Implementation :: PyPy
Classifier: License :: OSI Approved :: MIT License
Classifier: Operating System :: OS Independent
Requires-Python: >=3.8
License-File: LICENSE
Requires-Dist: numpy>=1.19.0
Provides-Extra: int-array
Provides-Extra: numba-opt
Requires-Dist: numba>=0.55.0; extra == "numba-opt"
Provides-Extra: cython-opt
Requires-Dist: cython>=3.2.4; extra == "cython-opt"
Dynamic: author
Dynamic: author-email
Dynamic: classifier
Dynamic: description
Dynamic: description-content-type
Dynamic: home-page
Dynamic: keywords
Dynamic: license-file
Dynamic: project-url
Dynamic: provides-extra
Dynamic: requires-dist
Dynamic: requires-python
Dynamic: summary
